pipeline_integrity/__init__.py
pipeline_integrity/i18n.py
pipeline_integrity/pipe.py
pipeline_integrity/defect/__init__.py
pipeline_integrity/defect/metal_loss.py
pipeline_integrity/method/__init__.py
pipeline_integrity/method/asme/__init__.py
pipeline_integrity/method/asme/b31g_1991.py
pipeline_integrity/method/asme/b31g_2012.py
pipeline_integrity/method/asme/locale/ru/LC_MESSAGES/messages.po
pipeline_integrity-1.6.dist-info/LICENSE
pipeline_integrity-1.6.dist-info/METADATA
pipeline_integrity-1.6.dist-info/WHEEL
pipeline_integrity-1.6.dist-info/top_level.txt
pipeline_integrity-1.6.dist-info/RECORD
