Metadata-Version: 2.1
Name: pipeline-integrity
Version: 1.6
Summary: Pipeline integrity calculation
Home-page: https://github.com/vb64/pipeline.integrity
Author: Vitaly Bogomolov
Author-email: mail@vitaly-bogomolov.ru
License: UNKNOWN
Project-URL: Bug Tracker, https://github.com/vb64/pipeline.integrity/issues
Platform: UNKNOWN
Classifier: Programming Language :: Python
Classifier: License :: OSI Approved :: MIT License
Classifier: Operating System :: OS Independent
Requires-Dist: py23==1.2
Requires-Dist: pipeline-material==1.0
